LICENSE
MANIFEST.in
README.rst
setup.py
bin/confu
con_fu.egg-info/PKG-INFO
con_fu.egg-info/SOURCES.txt
con_fu.egg-info/dependency_links.txt
con_fu.egg-info/requires.txt
con_fu.egg-info/top_level.txt
confu/__init__.py
confu/ansible.py
confu/aws.py
confu/cfn.py
confu/cli.py
confu/pkg.py
confu/settings.py
confu/shell/__init__.py
confu/shell/confue.bash