Metadata-Version: 1.1
Name: con-fu
Version: 0.1.7
Summary: Fu for con.
Home-page: https://github.com/bninja/confu
Author: Egon Spengler
Author-email: egon@gb.com
License: BSD
Platform: any
Classifier: Intended Audience :: Developers
Classifier: License :: OSI Approved :: BSD License
Classifier: Operating System :: OS Independent
Classifier: Programming Language :: Python
Classifier: Topic :: Internet :: WWW/HTTP :: Dynamic Content
Classifier: Topic :: Software Development :: Libraries :: Python Modules
